nit/__init__.py
nit/__main__.py
nit/code.py
nit_udasitharani-0.1.0.dist-info/LICENSE
nit_udasitharani-0.1.0.dist-info/METADATA
nit_udasitharani-0.1.0.dist-info/WHEEL
nit_udasitharani-0.1.0.dist-info/top_level.txt
nit_udasitharani-0.1.0.dist-info/RECORD
