Metadata-Version: 2.1
Name: nit-udasitharani
Version: 0.1.0
Summary: A tool to generate tiles from name initials.
Home-page: https://github.com/udasitharani/name-initials-tile-generator
Author: Udasi Tharani
Author-email: udasitharani@gmail.com
License: UNKNOWN
Platform: UNKNOWN
Classifier: Programming Language :: Python :: 3
Classifier: License :: OSI Approved :: MIT License
Classifier: Operating System :: OS Independent
Requires-Python: >=3.6
